[
    {
        "englishURN": 1607160,
        "collection": "riyadussalihin",
        "volumeNumber": 1,
        "bookNumber": 2,
        "bookName": "The Book About the Etiquette of Eating",
        "babNumber": "100.00",
        "babName": "Mentioning Bismillah before and saying Al-Hamdulillah after Eating",
        "hadithNumber": 728,
        "hadithText": "'Aishah (May Allah be pleased with her) reported: Messenger of Allah (ﷺ) said, \"When any of you wants to eat, he should mention the Name of Allah in the begining, (i.e., say Bismillah). If he forgets to do it in the beginning, he should say Bismillah awwalahu wa akhirahu (I begin with the Name of Allah at the beginning and at the end).\"<br><br><b>[At-Tirmidhi and Abu Dawud]</b>.<br><br></b>",
        "bookID": "2.0",
        "grade1": null,
        "grade2": "",
        "comments": "",
        "ourHadithNumber": 2,
        "matchingArabicURN": 1707240,
        "last_updated": "2020-08-16 22:09:35"
    },
    {
        "englishURN": 1607170,
        "collection": "riyadussalihin",
        "volumeNumber": 1,
        "bookNumber": 2,
        "bookName": "The Book About the Etiquette of Eating",
        "babNumber": "100.00",
        "babName": "Mentioning Bismillah before and saying Al-Hamdulillah after Eating",
        "hadithNumber": 729,
        "hadithText": "Jabir (May Allah be pleased with him) reported: I heard Messenger of Allah (ﷺ) saying, \"If a person mentions the Name of Allah upon entering his house or eating, Satan says, addressing his followers: 'You will find no where to spend the night and no dinner.' But if he enters without mentioning the Name of Allah, Satan says (to his followers); 'You have found (a place) to spend the night in, and if he does not mention the Name of Allah at the time of eating, Satan says: 'You have found (a place) to spend the night in as well as food.\"'<br><br><b>[Muslim]</b>.<br><br></b>",
        "bookID": "2.0",
        "grade1": null,
        "grade2": "",
        "comments": "",
        "ourHadithNumber": 3,
        "matchingArabicURN": 1707250,
        "last_updated": "2020-08-16 22:09:35"
    },
    {
        "englishURN": 1607180,
        "collection": "riyadussalihin",
        "volumeNumber": 1,
        "bookNumber": 2,
        "bookName": "The Book About the Etiquette of Eating",
        "babNumber": "100.00",
        "babName": null,
        "hadithNumber": 730,
        "hadithText": "Hudhaifah (May Allah be pleased with him) reported: When we attended a meal with the Messenger of Allah (ﷺ), we would not stretch forth our hands towards the food until he (ﷺ) would start eating first. Once, we were with him when a little girl rushed in as if someone was impelling her. She was about to lay her hand on the food when the Messenger of Allah (ﷺ) caught her hand. Then a bedouin came in rushing as if someone were pushing him. He (ﷺ) caught his hand also and said, \"Satan considers that food lawful for himself on which the Name of Allah is not mentioned. He (Satan) brought this girl to make the food lawful through her but I caught her hand. Then he brought the bedouin to make it lawful through him but I caught his hand too. By Him in Whose Hand my soul is, now Satan's hand is in my grasp along with their hands.\" Then he mentioned the Name of Allah and began to eat.<br><br><b>[Muslim]</b>.<br><br></b>",
        "bookID": "2.0",
        "grade1": null,
        "grade2": "",
        "comments": "",
        "ourHadithNumber": 4,
        "matchingArabicURN": 1707260,
        "last_updated": "2020-08-16 22:09:35"
    },
    {
        "englishURN": 1607190,
        "collection": "riyadussalihin",
        "volumeNumber": 1,
        "bookNumber": 2,
        "bookName": "The Book About the Etiquette of Eating",
        "babNumber": "100.00",
        "babName": "Mentioning Bismillah before and saying Al-Hamdulillah after Eating",
        "hadithNumber": 731,
        "hadithText": "Umaiyyah bin Makhshi (May Allah be pleased with him) reported: Messenger of Allah (ﷺ) was sitting while a man was eating food. That man did not mention the Name of Allah (before commencing to eat) till only a morsel of food was left. When he raised it to his mouth, he said: \"Bismillah awwalahu wa akhirahu (With the Name of Allah, in the beginning and in the end).\" Messenger of Allah (ﷺ) smiled at this and said, \"Satan had been eating with him but when he mentioned the Name of Allah, Satan vomited all that was in his stomach.\"<br><br><b>[Abu Dawud and An-Nasa'i]</b>.<br><br></b>",
        "bookID": "2.0",
        "grade1": null,
        "grade2": "",
        "comments": "",
        "ourHadithNumber": 5,
        "matchingArabicURN": 1707270,
        "last_updated": "2020-08-16 22:09:35"
    },
    {
        "englishURN": 1607200,
        "collection": "riyadussalihin",
        "volumeNumber": 1,
        "bookNumber": 2,
        "bookName": "The Book About the Etiquette of Eating",
        "babNumber": "100.00",
        "babName": null,
        "hadithNumber": 732,
        "hadithText": "'Aishah (May Allah be pleased with her) reported: The Messenger of Allah (ﷺ) was eating with his six Companions when a desert Arab came and ate up the food in two mouthfuls. Messenger of Allah (ﷺ) said, \"Had he mentioned the Name of Allah, it would have sufficed for all of you.\"<br><br><b>[At-Tirmidhi]</b>.<br><br></b>",
        "bookID": "2.0",
        "grade1": null,
        "grade2": "",
        "comments": "",
        "ourHadithNumber": 6,
        "matchingArabicURN": 1707280,
        "last_updated": "2020-08-16 22:09:35"
    },
    {
        "englishURN": 1607210,
        "collection": "riyadussalihin",
        "volumeNumber": 1,
        "bookNumber": 2,
        "bookName": "The Book About the Etiquette of Eating",
        "babNumber": "100.00",
        "babName": null,
        "hadithNumber": 734,
        "hadithText": "Mu'adh bin Anas (May Allah be pleased with him) reported: Messenger of Allah (ﷺ) said, \"He who has taken food and says at the end: 'Al- hamdu lillahi-lladhi at'amani hadha, wa razaqanihi min ghairi haulin minni wa la quwwatin (All praise is due to Allah Who has given me food to eat and provided it without any endeavour on my part or any power),' all his past sins will be forgiven.\" <br><br><b>[Abu Dawud and At- Tirmidhi]</b>.<br><br></b>",
        "bookID": "2.0",
        "grade1": null,
        "grade2": "",
        "comments": "",
        "ourHadithNumber": 8,
        "matchingArabicURN": 1707300,
        "last_updated": "2020-08-16 22:09:35"
    },
    {
        "englishURN": 1607220,
        "collection": "riyadussalihin",
        "volumeNumber": 1,
        "bookNumber": 2,
        "bookName": "The Book About the Etiquette of Eating",
        "babNumber": "101.00",
        "babName": "Prohibition of Criticizing Food",
        "hadithNumber": 736,
        "hadithText": "Jabir (May Allah be pleased with him) reported: The Prophet (ﷺ) asked for sauce and was told that there was nothing except vinegar. He asked for it and began to eat from it saying, \"How excellent is vinegar when eaten as sauce! How excellent is vinegar when eaten as Udm!\"<br><br><b>[Muslim]</b>.<br><br></b>",
        "bookID": "2.0",
        "grade1": null,
        "grade2": "",
        "comments": "",
        "ourHadithNumber": 10,
        "matchingArabicURN": 1707320,
        "last_updated": "2020-08-16 22:09:35"
    },
    {
        "englishURN": 1607230,
        "collection": "riyadussalihin",
        "volumeNumber": 1,
        "bookNumber": 2,
        "bookName": "The Book About the Etiquette of Eating",
        "babNumber": "104.00",
        "babName": "Eating from what is in front of One",
        "hadithNumber": 740,
        "hadithText": "Salamah bin Al-Akwa' (May Allah be pleased with him) reported on the authority of his father: A man ate with his left hand in the presence of Messenger of Allah (ﷺ), whereupon he said, \"Eat with your right hand.\" The man said: \"I cannot do that.\" Thereupon he (the Prophet (ﷺ)) said, \"May you not be able to do that.\" It was vanity that prevented him from doing it and he could not raise it (the right hand) up to his mouth afterwards.<br><br><b>[Muslim]</b>.<br><br></b>",
        "bookID": "2.0",
        "grade1": null,
        "grade2": "",
        "comments": "",
        "ourHadithNumber": 14,
        "matchingArabicURN": 1707355,
        "last_updated": "2020-08-16 22:09:35"
    },
    {
        "englishURN": 1607240,
        "collection": "riyadussalihin",
        "volumeNumber": 1,
        "bookNumber": 2,
        "bookName": "The Book About the Etiquette of Eating",
        "babNumber": "107.00",
        "babName": "Eating from the Side of the Vessel",
        "hadithNumber": 744,
        "hadithText": "'Abdullah bin Busr (May Allah be pleased with him) reported: The Prophet (ﷺ) had a large bowl called Al-Gharra', which would be carried by four men. One day, when the Companions finished their Duha (forenoon optional) prayer, Al-Gharra' was brought full of sopped bread, meat and broth, and they sat down around it. When their number increased, Messenger of Allah (ﷺ) sat down on his knees and rested on the soles of his feet. A bedouin said to him: \"What sort of sitting is that?\" Thereupon Messenger of Allah (ﷺ) said, \"Verily, Allah has made me a courteous slave not a fierce tyrant.\" Then he said, \"Eat from the sides of the bowl and leave the central part of it so that your food will be blessed.\"<br><br><b>[Abu Dawud]</b>.<br><br></b>",
        "bookID": "2.0",
        "grade1": null,
        "grade2": "",
        "comments": "",
        "ourHadithNumber": 18,
        "matchingArabicURN": 1707390,
        "last_updated": "2020-08-16 22:09:35"
    },
    {
        "englishURN": 1607250,
        "collection": "riyadussalihin",
        "volumeNumber": 1,
        "bookNumber": 2,
        "bookName": "The Book About the Etiquette of Eating",
        "babNumber": "108.00",
        "babName": "Undesirability of Eating in a Reclining Posture",
        "hadithNumber": 746,
        "hadithText": "Anas (May Allah be pleased with him) reported: I saw Messenger of Allah (ﷺ) eating some dates while sitting on his buttocks, with his legs raised.<br><br><b>[Muslim]</b>.<br><br></b>",
        "bookID": "2.0",
        "grade1": null,
        "grade2": "",
        "comments": "",
        "ourHadithNumber": 20,
        "matchingArabicURN": 1707410,
        "last_updated": "2020-08-16 22:09:35"
    },
    {
        "englishURN": 1607260,
        "collection": "riyadussalihin",
        "volumeNumber": 1,
        "bookNumber": 2,
        "bookName": "The Book About the Etiquette of Eating",
        "babNumber": "109.00",
        "babName": "Excellence of Eating with three Fingers and Licking them",
        "hadithNumber": 748,
        "hadithText": "Ka'b bin Malik (May Allah be pleased with him) reported: I saw Messenger of Allah (ﷺ) eating with three fingers (i.e., the thumb, the index finger and the middle finger) and licking them after having finished the food.<br><br><b>[Muslim]</b>.<br><br></b>",
        "bookID": "2.0",
        "grade1": null,
        "grade2": "",
        "comments": "",
        "ourHadithNumber": 22,
        "matchingArabicURN": 1707430,
        "last_updated": "2020-08-16 22:09:35"
    },
    {
        "englishURN": 1607270,
        "collection": "riyadussalihin",
        "volumeNumber": 1,
        "bookNumber": 2,
        "bookName": "The Book About the Etiquette of Eating",
        "babNumber": "109.00",
        "babName": null,
        "hadithNumber": 749,
        "hadithText": "Jabir (May Allah be pleased with him) reported: The Messenger of Allah (ﷺ) commanded the licking of fingers and the gleaning of the dish, saying, \"You do not know in which portion the blessing lies.\"<br><br><b>[Muslim]</b>.<br><br></b>",
        "bookID": "2.0",
        "grade1": null,
        "grade2": "",
        "comments": "",
        "ourHadithNumber": 23,
        "matchingArabicURN": 1707440,
        "last_updated": "2020-08-16 22:09:35"
    },
    {
        "englishURN": 1607280,
        "collection": "riyadussalihin",
        "volumeNumber": 1,
        "bookNumber": 2,
        "bookName": "The Book About the Etiquette of Eating",
        "babNumber": "109.00",
        "babName": null,
        "hadithNumber": 750,
        "hadithText": "Jabir (May Allah be pleased with him) reported: The Messenger of Allah (ﷺ) said, \"When a morsel of any of you falls, he should pick it up and remove any of the dirt on it and then eat it, and should not leave it for Satan nor should wipe his hand with towel until he has licked his fingers, for he does not know in what portion of the food the blessing lies.\"<br><br><b>[Muslim]</b>.<br><br></b>",
        "bookID": "2.0",
        "grade1": null,
        "grade2": "",
        "comments": "",
        "ourHadithNumber": 24,
        "matchingArabicURN": 1707450,
        "last_updated": "2020-08-16 22:09:35"
    },
    {
        "englishURN": 1607290,
        "collection": "riyadussalihin",
        "volumeNumber": 1,
        "bookNumber": 2,
        "bookName": "The Book About the Etiquette of Eating",
        "babNumber": "109.00",
        "babName": null,
        "hadithNumber": 751,
        "hadithText": "Jabir (May Allah be pleased with him) reported: The Messenger of Allah (ﷺ) said, \"Satan appears at every thing done by you; he appears even at one's dinner. When a morsel of any of you falls, he should pick it up and remove any dirt on it, and then eat it. He should not leave it for Satan, nor should he wipe his hand with the towel until he has licked his fingers, for he does not know in what portion of the food the blessing lies.\"<br><br><b>[Muslim]</b>.<br><br></b>",
        "bookID": "2.0",
        "grade1": null,
        "grade2": "",
        "comments": "",
        "ourHadithNumber": 25,
        "matchingArabicURN": 1707460,
        "last_updated": "2020-08-16 22:09:35"
    },
    {
        "englishURN": 1607300,
        "collection": "riyadussalihin",
        "volumeNumber": 1,
        "bookNumber": 2,
        "bookName": "The Book About the Etiquette of Eating",
        "babNumber": "109.00",
        "babName": null,
        "hadithNumber": 752,
        "hadithText": "Anas (May Allah be pleased with him) reported: Whenever the Messenger of Allah (ﷺ) ate food, he would lick his three fingers and say, \"If anyone of you drops a morsel of food, he should remove any dirt that may have stuck on it and then eat it, and should not leave it for Satan.\" He (ﷺ) also commanded us that we should glean the pot, saying, \"You do not know in which part of your food the blessings lies.\"<br><br><b>[Muslim]</b>.</b>",
        "bookID": "2.0",
        "grade1": null,
        "grade2": "",
        "comments": "",
        "ourHadithNumber": 26,
        "matchingArabicURN": 1707470,
        "last_updated": "2020-08-16 22:09:35"
    },
    {
        "englishURN": 1607310,
        "collection": "riyadussalihin",
        "volumeNumber": 1,
        "bookNumber": 2,
        "bookName": "The Book About the Etiquette of Eating",
        "babNumber": "109.00",
        "babName": "Excellence of Eating with three Fingers and Licking them",
        "hadithNumber": 753,
        "hadithText": "Sa'id bin Al-Harith reported: I asked Jabir (May Allah be pleased with him) whether it was obligatory to make Wudu' for Salat (prayer) after eating cooked food. He said: \"No, because in the lifetime of Messenger of Allah (ﷺ), such food was rarely available. We had no handkerchiefs, so when we ate such food we would wipe our fingers against our palms, forearms or (the sole of our) feet, and would offer Salat without fresh Wudu' (for prayer).\"<br><br><b>[Al- Bukhari]</b>.<br><br></b>",
        "bookID": "2.0",
        "grade1": null,
        "grade2": "",
        "comments": "",
        "ourHadithNumber": 27,
        "matchingArabicURN": 1707480,
        "last_updated": "2020-08-16 22:09:35"
    },
    {
        "englishURN": 1607320,
        "collection": "riyadussalihin",
        "volumeNumber": 1,
        "bookNumber": 2,
        "bookName": "The Book About the Etiquette of Eating",
        "babNumber": "110.00",
        "babName": null,
        "hadithNumber": 755,
        "hadithText": "Jabir bin 'Abdullah (May Allah be pleased with him) reported: The Messenger of Allah (ﷺ) said, \"The food of one person suffices for two, the food of two persons suffices for four persons, and the food of four persons suffices for eight persons.\"<br><br><b>[Muslim]</b>.<br><br></b>",
        "bookID": "2.0",
        "grade1": null,
        "grade2": "",
        "comments": "",
        "ourHadithNumber": 29,
        "matchingArabicURN": 1707500,
        "last_updated": "2020-08-16 22:09:35"
    },
    {
        "englishURN": 1607330,
        "collection": "riyadussalihin",
        "volumeNumber": 1,
        "bookNumber": 2,
        "bookName": "The Book About the Etiquette of Eating",
        "babNumber": "111.00",
        "babName": null,
        "hadithNumber": 757,
        "hadithText": "Ibn 'Abbas (May Allah be pleased with them) reported: The Messenger of Allah (ﷺ) said, \"Do not drink in one gulp like a camel, but in two or three (gulps). Mention the Name of Allah (i.e., say Bismillah) when you start drinking and praise Him (i.e., say Al-hamdu lillah) after you have finished (drinking).\"<br><br><b>[At- Tirmidhi]</b>.<br><br></b>",
        "bookID": "2.0",
        "grade1": null,
        "grade2": "",
        "comments": "",
        "ourHadithNumber": 31,
        "matchingArabicURN": 1707520,
        "last_updated": "2020-08-16 22:09:35"
    },
    {
        "englishURN": 1607340,
        "collection": "riyadussalihin",
        "volumeNumber": 1,
        "bookNumber": 2,
        "bookName": "The Book About the Etiquette of Eating",
        "babNumber": "111.00",
        "babName": "Etiquette of Drinking Water",
        "hadithNumber": 758,
        "hadithText": "Abu Qatadah (May Allah be pleased with him) reported: The Prophet (ﷺ) forbade breathing into the vessel while drinking.<br><br><b >[Al-Bukhari and Muslim]</b>.<br><br></b>",
        "bookID": "2.0",
        "grade1": null,
        "grade2": "",
        "comments": "",
        "ourHadithNumber": 32,
        "matchingArabicURN": 1707530,
        "last_updated": "2020-08-16 22:09:35"
    },
    {
        "englishURN": 1607350,
        "collection": "riyadussalihin",
        "volumeNumber": 1,
        "bookNumber": 2,
        "bookName": "The Book About the Etiquette of Eating",
        "babNumber": "111.00",
        "babName": null,
        "hadithNumber": 759,
        "hadithText": "Anas (May Allah be pleased with him) reported: Milk mixed with water was brought to the Messenger of Allah (ﷺ). On his right side was sitting a bedouin and on his left was sitting Abu Bakr (May Allah be pleased with him). He (ﷺ) drank from it and handed the rest to the bedouin saying, \"One who is on the right has preference, then again the one who is on the right.\"<br><br><b>[Al-Bukhari and Muslim]</b>.</b>",
        "bookID": "2.0",
        "grade1": null,
        "grade2": "",
        "comments": "",
        "ourHadithNumber": 33,
        "matchingArabicURN": 1707540,
        "last_updated": "2020-08-16 22:09:35"
    },
    {
        "englishURN": 1607360,
        "collection": "riyadussalihin",
        "volumeNumber": 1,
        "bookNumber": 2,
        "bookName": "The Book About the Etiquette of Eating",
        "babNumber": "111.00",
        "babName": null,
        "hadithNumber": 760,
        "hadithText": "Sahl bin Sa'd (May Allah be pleased with him) reported: A drink was brought to the Messenger of Allah (ﷺ) and he drank (some) from it. On his right was a boy and on his left were some elderly people. He (ﷺ) said to the boy, \"Would you permit me to give rest of this drink to these on my left?\" The boy said: \"O Messenger of Allah, I would certainly not give preference to anyone in anything that might come to me from you.\" So he (ﷺ) handed over the rest of the drink to him.<br><br><b>[Al-Bukhari and Muslim]</b>.<br><br></b>",
        "bookID": "2.0",
        "grade1": null,
        "grade2": "",
        "comments": "",
        "ourHadithNumber": 34,
        "matchingArabicURN": 1707550,
        "last_updated": "2020-08-16 22:09:35"
    },
    {
        "englishURN": 1607370,
        "collection": "riyadussalihin",
        "volumeNumber": 1,
        "bookNumber": 2,
        "bookName": "The Book About the Etiquette of Eating",
        "babNumber": "112.00",
        "babName": null,
        "hadithNumber": 762,
        "hadithText": "Abu Hurairah (May Allah be pleased with him) reported: The Messenger of Allah (ﷺ) prohibited drinking directly out of the mouth of a water- skin.<br><br><b>[Al-Bukhari and Muslim]</b>.<br><br></b>",
        "bookID": "2.0",
        "grade1": null,
        "grade2": "",
        "comments": "",
        "ourHadithNumber": 36,
        "matchingArabicURN": 1707570,
        "last_updated": "2020-08-16 22:09:35"
    },
    {
        "englishURN": 1607380,
        "collection": "riyadussalihin",
        "volumeNumber": 1,
        "bookNumber": 2,
        "bookName": "The Book About the Etiquette of Eating",
        "babNumber": "112.00",
        "babName": null,
        "hadithNumber": 763,
        "hadithText": "Umm Thabit Kabshah (May Allah be pleased with her), daughter of Thabit (May Allah be pleased with him) and the sister of Hassan bin Thabit, the Prophet's poet) reported: The Messenger of Allah (ﷺ) visited me and drank some water from a hanging water-skin while he was in a standing posture. So, I stood up and cut off the mouth (of that water-skin).<br><br><b>[At- Tirmidhi]</b>.<br><br><br><p>\nAn-Nawawi said that the reason why she did this was to preserve the part of the water-skin which the lips of Messenger of Allah (ﷺ) touched, gain blessings from it, and preserve it from dishonor. This narration is understood to show permissibility whereas the previous two narrations are to show what is better and closer to perfection. Allah knows best.</b>",
        "bookID": "2.0",
        "grade1": null,
        "grade2": "",
        "comments": "",
        "ourHadithNumber": 37,
        "matchingArabicURN": 1707580,
        "last_updated": "2020-08-16 22:09:35"
    },
    {
        "englishURN": 1607390,
        "collection": "riyadussalihin",
        "volumeNumber": 1,
        "bookNumber": 2,
        "bookName": "The Book About the Etiquette of Eating",
        "babNumber": "113.00",
        "babName": null,
        "hadithNumber": 765,
        "hadithText": "Ibn 'Abbas (May Allah be pleased with them) reported: The Prophet (ﷺ) prohibited us from breathing into the drinking vessel or blowing in it.<br><br><b>[At-Tirmidhi]</b>.</b>",
        "bookID": "2.0",
        "grade1": null,
        "grade2": "",
        "comments": "",
        "ourHadithNumber": 39,
        "matchingArabicURN": 1707600,
        "last_updated": "2020-08-16 22:09:35"
    },
    {
        "englishURN": 1607400,
        "collection": "riyadussalihin",
        "volumeNumber": 1,
        "bookNumber": 2,
        "bookName": "The Book About the Etiquette of Eating",
        "babNumber": "114.00",
        "babName": null,
        "hadithNumber": 767,
        "hadithText": "An-Nazzal bin Sabrah (May Allah be pleased with him) reported: 'Ali bin Abu Talib (May Allah be pleased with him) arrived at Bab Ar-Rahbah (in Kufah) and drank water in a standing posture. Then he said: \"I saw the Messenger of Allah (ﷺ) doing what you have seen me doing.\"<br><br><b>[Al-Bukhari]</b>.</b>",
        "bookID": "2.0",
        "grade1": null,
        "grade2": "",
        "comments": "",
        "ourHadithNumber": 41,
        "matchingArabicURN": 1707620,
        "last_updated": "2020-08-16 22:09:35"
    },
    {
        "englishURN": 1607410,
        "collection": "riyadussalihin",
        "volumeNumber": 1,
        "bookNumber": 2,
        "bookName": "The Book About the Etiquette of Eating",
        "babNumber": "114.00",
        "babName": null,
        "hadithNumber": 768,
        "hadithText": "Ibn 'Umar (May Allah be pleased with them) reported: During the lifetime of the Messenger of Allah (ﷺ) we would eat while walking and would drink while standing.<br><br><b>[At- Tirmidhi]</b>.<br><br></b>",
        "bookID": "2.0",
        "grade1": null,
        "grade2": "",
        "comments": "",
        "ourHadithNumber": 42,
        "matchingArabicURN": 1707630,
        "last_updated": "2020-08-16 22:09:35"
    },
    {
        "englishURN": 1607420,
        "collection": "riyadussalihin",
        "volumeNumber": 1,
        "bookNumber": 2,
        "bookName": "The Book About the Etiquette of Eating",
        "babNumber": "114.00",
        "babName": null,
        "hadithNumber": 769,
        "hadithText": "'Amr bin Shu'aib on the authority of his father and grandfather reported: I saw Messenger of Allah (ﷺ) drink standing, or sitting.<br><br><b>[At-Tirmidhi]</b>.<br><br></b>",
        "bookID": "2.0",
        "grade1": null,
        "grade2": "",
        "comments": "",
        "ourHadithNumber": 43,
        "matchingArabicURN": 1707640,
        "last_updated": "2020-08-16 22:09:35"
    },
    {
        "englishURN": 1607430,
        "collection": "riyadussalihin",
        "volumeNumber": 1,
        "bookNumber": 2,
        "bookName": "The Book About the Etiquette of Eating",
        "babNumber": "114.00",
        "babName": null,
        "hadithNumber": 770,
        "hadithText": "Anas (May Allah be pleased with him) reported: The Prophet (ﷺ) forbade us from drinking while standing. Qatadah reported: \"We asked him: 'What about eating?\"' He said: \"That is even worse, (or may be he said) more detestable.\"<br><br>Another narration is: The Messenger of Allah (ﷺ) reprimanded [us] for drinking while standing.<br><br><b>[Muslim]</b>.</b>",
        "bookID": "2.0",
        "grade1": null,
        "grade2": "",
        "comments": "",
        "ourHadithNumber": 44,
        "matchingArabicURN": 1707650,
        "last_updated": "2020-08-16 22:09:35"
    },
    {
        "englishURN": 1607440,
        "collection": "riyadussalihin",
        "volumeNumber": 1,
        "bookNumber": 2,
        "bookName": "The Book About the Etiquette of Eating",
        "babNumber": "114.00",
        "babName": null,
        "hadithNumber": 771,
        "hadithText": "Abu Hurairah (May Allah be pleased with him) reported: The Messenger of Allah (ﷺ) said, \"None of you should drink standing; and if any one forgets, he must vomit.\"<br><br><b>[Muslim]</b>.<br><br></b>",
        "bookID": "2.0",
        "grade1": null,
        "grade2": "",
        "comments": "",
        "ourHadithNumber": 45,
        "matchingArabicURN": 1707660,
        "last_updated": "2020-08-16 22:09:35"
    },
    {
        "englishURN": 1607450,
        "collection": "riyadussalihin",
        "volumeNumber": 1,
        "bookNumber": 2,
        "bookName": "The Book About the Etiquette of Eating",
        "babNumber": "116.00",
        "babName": "Permissibility of drinking water from clean Vessels of all types except Gold and Silver ones",
        "hadithNumber": 774,
        "hadithText": "'Abdullah bin Zaid (May Allah be pleased with him) reported: The Prophet (ﷺ) visited us and we brought water for him in a brass vessel for his ablution and he performed ablution.<br><br><b>[Al- Bukhari]</b>.<br><br></b>",
        "bookID": "2.0",
        "grade1": null,
        "grade2": "",
        "comments": "",
        "ourHadithNumber": 48,
        "matchingArabicURN": 1707691,
        "last_updated": "2020-08-16 22:09:35"
    },
    {
        "englishURN": 1607460,
        "collection": "riyadussalihin",
        "volumeNumber": 1,
        "bookNumber": 2,
        "bookName": "The Book About the Etiquette of Eating",
        "babNumber": "116.00",
        "babName": null,
        "hadithNumber": 775,
        "hadithText": "Jabir (May Allah be pleased with him) reported: The Messenger of Allah (ﷺ) visited the house of a man of the Ansar with one of his Companions and said to him, \"If you have some water in the water-skin left over from last night, give it to us for drinking; otherwise, we shall drink from some stream directly.\"<br><br><b>[Al- Bukhari]</b>.<br><br></b>",
        "bookID": "2.0",
        "grade1": null,
        "grade2": "",
        "comments": "",
        "ourHadithNumber": 49,
        "matchingArabicURN": 1707692,
        "last_updated": "2020-08-16 22:09:35"
    },
    {
        "englishURN": 1607470,
        "collection": "riyadussalihin",
        "volumeNumber": 1,
        "bookNumber": 2,
        "bookName": "The Book About the Etiquette of Eating",
        "babNumber": "116.00",
        "babName": "Permissibility of drinking water from clean Vessels of all types except Gold and Silver ones",
        "hadithNumber": 776,
        "hadithText": "Hudhaifah (May Allah be pleased with him) reported: The Prophet (ﷺ) prohibited us from wearing brocade or silk and drinking out of gold or silver vessels and said, \"These are meant for them (disbelievers) in this world and for you in the Hereafter.\"<br><br><b >[Al-Bukhari and Muslim]</b>.<br><br></b>",
        "bookID": "2.0",
        "grade1": null,
        "grade2": "",
        "comments": "",
        "ourHadithNumber": 50,
        "matchingArabicURN": 1707700,
        "last_updated": "2020-08-16 22:09:35"
    },
    {
        "englishURN": 1607480,
        "collection": "riyadussalihin",
        "volumeNumber": 1,
        "bookNumber": 2,
        "bookName": "The Book About the Etiquette of Eating",
        "babNumber": "116.00",
        "babName": null,
        "hadithNumber": 777,
        "hadithText": "Umm Salamah (May Allah be pleased with her) reported: The Messenger of Allah (ﷺ) said, \"He who drinks from the vessel of silver kindles the Fire (of Hell) in his belly.\"<br><br><b>[Al-Bukhari and Muslim]</b>.<br><br>A narration in Muslim is: The Messenger of Allah (ﷺ) said, \"Surely, he who eats or drinks in gold and silver vessels fills his belly with Hell-fire.\"<br><br></b>",
        "bookID": "2.0",
        "grade1": null,
        "grade2": "",
        "comments": "",
        "ourHadithNumber": 51,
        "matchingArabicURN": 1707710,
        "last_updated": "2020-08-16 22:09:35"
    },
    {
        "englishURN": 1607155,
        "collection": "riyadussalihin",
        "volumeNumber": 1,
        "bookNumber": 2,
        "bookName": "The Book About the Etiquette of Eating",
        "babNumber": "100.00",
        "babName": "Mentioning Bismillah before and saying Al-Hamdulillah after Eating",
        "hadithNumber": 727,
        "hadithText": "'Umar bin Abu Salamah (May Allah be pleased with him) reported: Messenger of Allah (ﷺ), said to me, \"Mention Allah's Name (i.e., say Bismillah before starting eating), eat with your right hand, and eat from what is near you.\"<br><p>\n<p><br><p>\n<b>[Al-Bukhari and Muslim]</b>.</b>",
        "bookID": "2.0",
        "grade1": null,
        "grade2": "",
        "comments": "",
        "ourHadithNumber": 1,
        "matchingArabicURN": 1707230,
        "last_updated": "2020-08-16 22:09:35"
    },
    {
        "englishURN": 1607205,
        "collection": "riyadussalihin",
        "volumeNumber": 1,
        "bookNumber": 2,
        "bookName": "The Book About the Etiquette of Eating",
        "babNumber": "100.00",
        "babName": "Mentioning Bismillah before and saying Al-Hamdulillah after Eating",
        "hadithNumber": 733,
        "hadithText": "Abu Umamah (May Allah be pleased with him) reported: Whenever the Prophet (ﷺ) finished a meal, he would say: \"Al-hamdu lillahi hamdan kathiran taiyyiban mubarakan fihi, ghaira makfiyyin wa la muwadda`in, wa la mustaghnan `anhu, Rabbuna. (All praise is due to Allah, praise which is abundant, pure, and full of blessings, which is indispensable and to which one cannot be indifferent).''  \r<br><p>\n<p>\r<br><p>\n<b>[Al-Bukhari]</b>.</b>",
        "bookID": "2.0",
        "grade1": null,
        "grade2": "",
        "comments": "",
        "ourHadithNumber": 7,
        "matchingArabicURN": 1707290,
        "last_updated": "2020-08-16 22:09:35"
    },
    {
        "englishURN": 1607215,
        "collection": "riyadussalihin",
        "volumeNumber": 1,
        "bookNumber": 2,
        "bookName": "The Book About the Etiquette of Eating",
        "babNumber": "101.00",
        "babName": "Prohibition of Criticizing Food",
        "hadithNumber": 735,
        "hadithText": "Abu Hurairah (May Allah be pleased with him) reported: Messenger of Allah (ﷺ) never found fault with food. If he had inclination to eating it, he would eat; and if he disliked it, he would leave it.<br><p>\n<p><br><p>\n<b>[Al-Bukhari and Muslim]</b>.</b>",
        "bookID": "2.0",
        "grade1": null,
        "grade2": "",
        "comments": "",
        "ourHadithNumber": 9,
        "matchingArabicURN": 1707310,
        "last_updated": "2020-08-16 22:09:35"
    },
    {
        "englishURN": 1607221,
        "collection": "riyadussalihin",
        "volumeNumber": 1,
        "bookNumber": 2,
        "bookName": "The Book About the Etiquette of Eating",
        "babNumber": "102.00",
        "babName": null,
        "hadithNumber": 737,
        "hadithText": "Abu Hurairah (May Allah be pleased with him) reported: The Messenger of Allah (ﷺ) said, \"When any of you is invited to a meal, he should accept the invitation. If he is observing Saum (fasting), he should supplicate for the betterment of the host and if he is not fasting, he should eat.\"<br><p>\n<p><br><p>\n<b>[Muslim]</b>.</b>",
        "bookID": "2.0",
        "grade1": null,
        "grade2": "",
        "comments": "",
        "ourHadithNumber": 11,
        "matchingArabicURN": 1707330,
        "last_updated": "2020-08-16 22:09:35"
    },
    {
        "englishURN": 1607222,
        "collection": "riyadussalihin",
        "volumeNumber": 1,
        "bookNumber": 2,
        "bookName": "The Book About the Etiquette of Eating",
        "babNumber": "103.00",
        "babName": "What should one say to the Host if an uninvited Person is accompanied with an invited Person",
        "hadithNumber": 738,
        "hadithText": "Abu Mas'ud Al-Badri (May Allah be pleased with him) reported: A man prepared some food especially for the Prophet (ﷺ) and invited him along with four others. But a man accompanied him. Having arrived at the door, Messenger of Allah (ﷺ) said to the host, \"This person has followed us. You may allow him, if you like, and if you like he will return.\" He said: \"O Messenger of Allah, I allow him, too.\"<br><p>\n<p><br><p>\n<b>[Al-Bukhari and Muslim]</b>.</b>",
        "bookID": "2.0",
        "grade1": null,
        "grade2": "",
        "comments": "",
        "ourHadithNumber": 12,
        "matchingArabicURN": 1707340,
        "last_updated": "2020-08-16 22:09:35"
    },
    {
        "englishURN": 1607223,
        "collection": "riyadussalihin",
        "volumeNumber": 1,
        "bookNumber": 2,
        "bookName": "The Book About the Etiquette of Eating",
        "babNumber": "104.00",
        "babName": "Eating from what is in front of One",
        "hadithNumber": 739,
        "hadithText": "'Umar bin Abu Salamah (May Allah be pleased with them) reported: I was a boy under the care of Messenger of Allah (ﷺ), and as my hand used to wander around in the dish, he (ﷺ) said to me once, \"Mention Allah's Name (i.e., say Bismillah), eat with your right hand, and eat from what is in front of you.\"<br><p>\n<p><br><p>\n<b>[Al-Bukhari and Muslim]</b>.</b>",
        "bookID": "2.0",
        "grade1": null,
        "grade2": "",
        "comments": "",
        "ourHadithNumber": 13,
        "matchingArabicURN": 1707350,
        "last_updated": "2020-08-16 22:09:35"
    },
    {
        "englishURN": 1607232,
        "collection": "riyadussalihin",
        "volumeNumber": 1,
        "bookNumber": 2,
        "bookName": "The Book About the Etiquette of Eating",
        "babNumber": "105.00",
        "babName": "Prohibition of Eating Two Date-fruits Simultaneously",
        "hadithNumber": 741,
        "hadithText": "Jabalah bin Suhaim reported: We were with 'Abdullah bin Az-Zubair (May Allah be pleased with them) in a time of famine, then we were provided with dates. (Once) when we were eating, 'Abdullah bin 'Umar (May Allah be pleased with them) passed by us and said: \"Do not eat two dates together, for Messenger of Allah (ﷺ) prohibited it, unless one seeks permission from his brother (partner).\"<br><p>\n<p><br><p>\n<b>[Al-Bukhari and Muslim]</b>.</b>",
        "bookID": "2.0",
        "grade1": null,
        "grade2": "",
        "comments": "",
        "ourHadithNumber": 15,
        "matchingArabicURN": 1707360,
        "last_updated": "2020-08-16 22:09:35"
    },
    {
        "englishURN": 1607234,
        "collection": "riyadussalihin",
        "volumeNumber": 1,
        "bookNumber": 2,
        "bookName": "The Book About the Etiquette of Eating",
        "babNumber": "106.00",
        "babName": "What should a Person say or do when he eats but is not satisfied",
        "hadithNumber": 742,
        "hadithText": "Wahshi bin Harb (May Allah be pleased with him) reported: Some of the Companions of Messenger of Allah (ﷺ) said: \"We eat but are not satisfied.\" He (ﷺ) said, \"Perhaps you eat separately.\" The Companions replied in affirmative. He then said: \"Eat together and mention the Name of Allah over your food. It will be blessed for you.\"<br><p>\n<p><br><p>\n<b>[Abu Dawud]</b>.</b>",
        "bookID": "2.0",
        "grade1": null,
        "grade2": "",
        "comments": "",
        "ourHadithNumber": 16,
        "matchingArabicURN": 1707370,
        "last_updated": "2020-08-16 22:09:35"
    },
    {
        "englishURN": 1607236,
        "collection": "riyadussalihin",
        "volumeNumber": 1,
        "bookNumber": 2,
        "bookName": "The Book About the Etiquette of Eating",
        "babNumber": "107.00",
        "babName": null,
        "hadithNumber": 743,
        "hadithText": "Ibn 'Abbas (May Allah be pleased with them) reported: The Prophet (ﷺ) said, \"Blessing descends upon food in its middle, so eat from the sides of the vessel and do not eat from its middle.\"<br><p>\n<p><br><p>\n<b>[Abu Dawud and At-Tirmidhi]</b>.</b>",
        "bookID": "2.0",
        "grade1": null,
        "grade2": "",
        "comments": "",
        "ourHadithNumber": 17,
        "matchingArabicURN": 1707380,
        "last_updated": "2020-08-16 22:09:35"
    },
    {
        "englishURN": 1607245,
        "collection": "riyadussalihin",
        "volumeNumber": 1,
        "bookNumber": 2,
        "bookName": "The Book About the Etiquette of Eating",
        "babNumber": "108.00",
        "babName": null,
        "hadithNumber": 745,
        "hadithText": "Abu Juhaifah Wahb bin 'Abdullah (May Allah be pleased with him) reported: Messenger of Allah (ﷺ) said, \"I do not eat reclining (against a pillow).\"<br><p>\n<p><br><p>\n<b>[Al-Bukhari]</b>.</b>",
        "bookID": "2.0",
        "grade1": null,
        "grade2": "",
        "comments": "",
        "ourHadithNumber": 19,
        "matchingArabicURN": 1707400,
        "last_updated": "2020-08-16 22:09:35"
    },
    {
        "englishURN": 1607255,
        "collection": "riyadussalihin",
        "volumeNumber": 1,
        "bookNumber": 2,
        "bookName": "The Book About the Etiquette of Eating",
        "babNumber": "109.00",
        "babName": "Excellence of Eating with three Fingers and Licking them",
        "hadithNumber": 747,
        "hadithText": "Ibn 'Abbas (May Allah be pleased with them) reported: Messenger of Allah (ﷺ) said, \"When one of you finishes eating, he should not wipe his fingers until he has licked them himself or has given them to someone else to lick for him.\"<br><p>\n<p><br><p>\n<b>[Al-Bukhari and Muslim]</b>.</b>",
        "bookID": "2.0",
        "grade1": null,
        "grade2": "",
        "comments": "",
        "ourHadithNumber": 21,
        "matchingArabicURN": 1707420,
        "last_updated": "2020-08-16 22:09:35"
    },
    {
        "englishURN": 1607315,
        "collection": "riyadussalihin",
        "volumeNumber": 1,
        "bookNumber": 2,
        "bookName": "The Book About the Etiquette of Eating",
        "babNumber": "110.00",
        "babName": null,
        "hadithNumber": 754,
        "hadithText": "Abu Hurairah (May Allah be pleased with him) reported: The Messenger of Allah (ﷺ) said, \"The food of two persons suffices for three persons, and the food of three persons suffices for four persons.\"<br><p>\n<p><br><p>\n<b>[Al-Bukhari and Muslim]</b>.</b>",
        "bookID": "2.0",
        "grade1": null,
        "grade2": "",
        "comments": "",
        "ourHadithNumber": 28,
        "matchingArabicURN": 1707490,
        "last_updated": "2020-08-16 22:09:35"
    },
    {
        "englishURN": 1607325,
        "collection": "riyadussalihin",
        "volumeNumber": 1,
        "bookNumber": 2,
        "bookName": "The Book About the Etiquette of Eating",
        "babNumber": "111.00",
        "babName": null,
        "hadithNumber": 756,
        "hadithText": "Anas (May Allah be pleased with him) reported: The Messenger of Allah (ﷺ) used to breathe three times in the course of a drink (he used to drink in three gulps).<br><p>\n<p><br><p>\n<b>[Al-Bukhari and Muslim]</b>.</b>",
        "bookID": "2.0",
        "grade1": null,
        "grade2": "",
        "comments": "",
        "ourHadithNumber": 30,
        "matchingArabicURN": 1707510,
        "last_updated": "2020-08-16 22:09:35"
    },
    {
        "englishURN": 1607365,
        "collection": "riyadussalihin",
        "volumeNumber": 1,
        "bookNumber": 2,
        "bookName": "The Book About the Etiquette of Eating",
        "babNumber": "112.00",
        "babName": null,
        "hadithNumber": 761,
        "hadithText": "Abu Sa'id Al-Khudri (May Allah be pleased with him) reported: The Messenger of Allah (ﷺ) forbade turning the water-skin upside down and drinking directly from its mouth.<br><p>\n<p><br><p>\n<b>[Al-Bukhari and Muslim]</b>.</b>",
        "bookID": "2.0",
        "grade1": null,
        "grade2": "",
        "comments": "",
        "ourHadithNumber": 35,
        "matchingArabicURN": 1707560,
        "last_updated": "2020-08-16 22:09:35"
    },
    {
        "englishURN": 1607385,
        "collection": "riyadussalihin",
        "volumeNumber": 1,
        "bookNumber": 2,
        "bookName": "The Book About the Etiquette of Eating",
        "babNumber": "113.00",
        "babName": null,
        "hadithNumber": 764,
        "hadithText": "Abu Sa'id Al-Khudri (May Allah be pleased with him) reported: The Messenger of Allah (ﷺ) prohibited us blowing in the drinking water. A man said: \"O Messenger of Allah! Sometimes I see some litter floating about on the surface. What should I do then?\" He (ﷺ) replied, \"Pour them out.\" Then the man said: \"My thirst is not quenched with one draught.\" Messenger of Allah (ﷺ) said, \"Then put away the cup from your mouth (in between three gulps), and take breath.\"<br><p>\n<p><br><p>\n<b>[At-Tirmidhi]</b>.</b>",
        "bookID": "2.0",
        "grade1": null,
        "grade2": "",
        "comments": "",
        "ourHadithNumber": 38,
        "matchingArabicURN": 1707590,
        "last_updated": "2020-08-16 22:09:35"
    },
    {
        "englishURN": 1607395,
        "collection": "riyadussalihin",
        "volumeNumber": 1,
        "bookNumber": 2,
        "bookName": "The Book About the Etiquette of Eating",
        "babNumber": "114.00",
        "babName": null,
        "hadithNumber": 766,
        "hadithText": "Ibn 'Abbas (May Allah be pleased with them) reported: I served the Messenger of Allah (ﷺ) Zamzam water to drink and he drank it while he was standing.<br><p>\n<p><br><p>\n<b>[Al-Bukhari and Muslim]</b>.</b>",
        "bookID": "2.0",
        "grade1": null,
        "grade2": "",
        "comments": "",
        "ourHadithNumber": 40,
        "matchingArabicURN": 1707610,
        "last_updated": "2020-08-16 22:09:35"
    },
    {
        "englishURN": 1607445,
        "collection": "riyadussalihin",
        "volumeNumber": 1,
        "bookNumber": 2,
        "bookName": "The Book About the Etiquette of Eating",
        "babNumber": "115.00",
        "babName": null,
        "hadithNumber": 772,
        "hadithText": "Abu Qatadah (May Allah be pleased with him) reported: The Messenger of Allah (ﷺ) said, \"He who serves others with drinking water should be the last to drink himself.\"<br><p>\n<p><br><p>\n<b>[At-Tirmidhi]</b>.</b>",
        "bookID": "2.0",
        "grade1": null,
        "grade2": "",
        "comments": "",
        "ourHadithNumber": 46,
        "matchingArabicURN": 1707670,
        "last_updated": "2020-08-16 22:09:35"
    },
    {
        "englishURN": 1607447,
        "collection": "riyadussalihin",
        "volumeNumber": 1,
        "bookNumber": 2,
        "bookName": "The Book About the Etiquette of Eating",
        "babNumber": "116.00",
        "babName": null,
        "hadithNumber": 773,
        "hadithText": "Anas bin Malik (May Allah be pleased with him) reported: Once the time for As-Salat (the prayer) approached. Those whose houses were near, went to their houses (to perform Wudu') while some of the people remained with the Messenger of Allah (ﷺ). A stone (containing some water) bowl was brought for him. It was too small for him to spread his hand over it. He performed his Wudu' and it (the water) sufficed for all the others also. Anas was asked: \"How many of you were present there?\" He said: \"Eighty or more.\"<br><p>\n<p><br><p>\n<b>[Al-Bukhari and Muslim].</b> This is Al-Bukhari's version.<br><br><br><p>\nIn Muslim's version \"'that Allah's Apostle (ﷺ) called for a container of water so he was given a vessel that had some water.' Anas said 'Then I started looking at the water spouting from his fingers. Then I estimated (the persons) and they were between seventy and eighty.'\"</b>",
        "bookID": "2.0",
        "grade1": null,
        "grade2": "",
        "comments": "",
        "ourHadithNumber": 47,
        "matchingArabicURN": 1707680,
        "last_updated": "2020-08-16 22:09:35"
    }
]